qFS/__init__.py
qFS/qFS.py
qfs-0.0.2.dist-info/licenses/LICENSE
qfs-0.0.2.dist-info/METADATA
qfs-0.0.2.dist-info/WHEEL
qfs-0.0.2.dist-info/top_level.txt
qfs-0.0.2.dist-info/RECORD
