Metadata-Version: 2.4
Name: qFS
Version: 0.0.2
Summary: A Python package for Quantum Feature Selection (qFS).
Author: Ayushmaan Singh
Classifier: Programming Language :: Python :: 3
Classifier: License :: OSI Approved :: MIT License
Classifier: Operating System :: OS Independent
Requires-Python: >=3.7
License-File: LICENSE
Requires-Dist: numpy
Requires-Dist: scikit-learn
Dynamic: author
Dynamic: classifier
Dynamic: license-file
Dynamic: requires-dist
Dynamic: requires-python
Dynamic: summary
